IP_Connector/IpConnector.py
IP_Connector/NetworkSupervisor.py
IP_Connector/PrintRecord.py
IP_Connector/__init__.py
IP_Connector/json_maker.py
IP_Connector/automatic_email_sender/Sender.py
IP_Connector/automatic_email_sender/__init__.py
IP_Connector-0.0.2.dist-info/DESCRIPTION.rst
IP_Connector-0.0.2.dist-info/METADATA
IP_Connector-0.0.2.dist-info/RECORD
IP_Connector-0.0.2.dist-info/WHEEL
IP_Connector-0.0.2.dist-info/metadata.json
IP_Connector-0.0.2.dist-info/top_level.txt
